<?xml version="1.0" encoding="UTF-8"?>
<feature
      id="org.eclipse.ptp.cdt.compilers"
      label="%featureName"
      version="7.0.qualifier"
      provider-name="%providerName">

   <description url="http://eclipse.org/ptp">
      %description
   </description>

   <copyright>
      %copyright
   </copyright>

   <license url="%licenseURL">
      %license
   </license>

   <requires>
      <import feature="org.eclipse.cdt" version="8.0" match="greaterOrEqual"/>
   </requires>

   <plugin
         id="org.eclipse.ptp.cdt.compilers.core"
         download-size="0"
         install-size="0"
         version="0.0.0"
         unpack="false"/>

</feature>
